libsolace/Decorators.py
libsolace/Exceptions.py
libsolace/Kwargs.py
libsolace/Naming.py
libsolace/SolaceAPI.py
libsolace/SolaceCommandQueue.py
libsolace/SolaceNode.py
libsolace/SolaceProvision.py
libsolace/SolaceReply.py
libsolace/SolaceXMLBuilder.py
libsolace/__init__.py
libsolace/plugin.py
libsolace/settingsloader.py
libsolace/util.py
libsolace/xml2dict.py
libsolace/data/__init__.py
libsolace/data/semp-rpc-soltr_6_0.xsd
libsolace/data/semp-rpc-soltr_6_2.xsd
libsolace/data/semp-rpc-soltr_7_0.xsd
libsolace/data/semp-rpc-soltr_7_1.xsd
libsolace/items/NullPlugin.py
libsolace/items/SolaceACLProfile.py
libsolace/items/SolaceBridge.py
libsolace/items/SolaceClientProfile.py
libsolace/items/SolaceQueue.py
libsolace/items/SolaceUser.py
libsolace/items/SolaceUsers.py
libsolace/items/SolaceVPN.py
libsolace/items/__init__.py
libsolace/plugins/CMDBClient.py
libsolace/plugins/InfluxDBClient.py
libsolace/plugins/NamingStandard.py
libsolace/plugins/OpenTSDBClient.py
libsolace/plugins/Utilities.py
libsolace/plugins/XMLAPI.py
libsolace/plugins/YAMLClient.py
libsolace/plugins/ZoinksNamingStandard.py
libsolace/plugins/__init__.py
libsolace-0.3.0.data/scripts/solace-provision.py
libsolace-0.3.0.dist-info/LICENSE.TXT
libsolace-0.3.0.dist-info/LICENSE.md
libsolace-0.3.0.dist-info/METADATA
libsolace-0.3.0.dist-info/WHEEL
libsolace-0.3.0.dist-info/top_level.txt
libsolace-0.3.0.dist-info/RECORD
