Metadata-Version: 2.1
Name: libsolace
Version: 0.3.0
Summary: Solace Provisioning Helper using the Solace SEMP XML API
Home-page: https://github.com/ExalDraen/python-libsolace
Author: Alexander Hermes
Author-email: night_lynx@hotmail.com
License: UNKNOWN
Keywords: solace
Platform: UNKNOWN
Classifier: Development Status :: 3 - Alpha
Classifier: Intended Audience :: Developers
Classifier: License :: OSI Approved :: MIT License
Classifier: Operating System :: POSIX
Classifier: Programming Language :: Python :: 2.7
Requires-Python: >=2.7,<=3.0
Requires-Dist: simplejson (<4.0.0,>=3.5.3)
Requires-Dist: urllib3 (<2.0.0,>=1.9)
Requires-Dist: lxml (<4.0.0,>=3.3.5)
Requires-Dist: pyyaml (<4.0.0,>=3.11)
